airam/__init__.py
airam-0.0.1.dist-info/METADATA
airam-0.0.1.dist-info/WHEEL
airam-0.0.1.dist-info/top_level.txt
airam-0.0.1.dist-info/RECORD
